mmdb/__init__.py
mmdb/__main__.py
mmdb/cli.py
mmdb/models.py
mmdb/rsc.py
mmdb-0.1.0.dist-info/entry_points.txt
mmdb-0.1.0.dist-info/LICENSE
mmdb-0.1.0.dist-info/WHEEL
mmdb-0.1.0.dist-info/METADATA
mmdb-0.1.0.dist-info/RECORD
