Metadata-Version: 2.1
Name: mmdb
Version: 0.1.0
Summary: 
License: MIT
Author: Leon Rendel
Author-email: 108236246+cercide@users.noreply.github.com
Requires-Python: >=3.7,<4.0.0
Classifier: License :: OSI Approved :: MIT License
Classifier: Programming Language :: Python :: 3
Classifier: Programming Language :: Python :: 3.7
Classifier: Programming Language :: Python :: 3.8
Classifier: Programming Language :: Python :: 3.9
Classifier: Programming Language :: Python :: 3.10
Classifier: Programming Language :: Python :: 3.11
Provides-Extra: cli
Provides-Extra: docs
Provides-Extra: testing
Requires-Dist: Sphinx (>=5.0,<6.0); extra == "docs"
Requires-Dist: maxminddb (>=2.0,<3.0)
Requires-Dist: mmdb-writer (>=0.1.1,<0.2.0)
Requires-Dist: netaddr (>=0.7.0,<1.0)
Requires-Dist: pre-commit (>=2.0,<3.0); extra == "testing"
Requires-Dist: pydantic (>=1.10.0,<2.0)
Requires-Dist: pytest (>=7.2,<8.0); extra == "testing"
Requires-Dist: pytest-cov (>=4.0.0,<5.0.0); extra == "testing"
Requires-Dist: sphinx-pydantic (>=0.1,<1.0); extra == "docs"
Requires-Dist: sphinx-rtd-theme (>=1.0,<2.0); extra == "docs" or extra == "docs"
Requires-Dist: tox (>=3.0,<4.0); extra == "testing"
Requires-Dist: tox-poetry (>=0.5,<1.0); extra == "testing"
Requires-Dist: tqdm (>=4.0,<5.0)
Requires-Dist: typer (>=0.1.0,<1.0); extra == "cli"
